archivenow/__init__.py
archivenow/archivenow.py
archivenow/handlers/cc_handler.py
archivenow/handlers/ia_handler.py
archivenow/handlers/is_handler.py
archivenow/handlers/mg_handler.py
archivenow/handlers/st_handler.py
archivenow/handlers/warc_handler.py
archivenow/handlers/wc_handler.py
archivenow/static/ajax-loader.gif
archivenow/templates/api.txt
archivenow/templates/index.html
archivenow-2020.7.18.12.19.44.dist-info/LICENSE
archivenow-2020.7.18.12.19.44.dist-info/METADATA
archivenow-2020.7.18.12.19.44.dist-info/WHEEL
archivenow-2020.7.18.12.19.44.dist-info/entry_points.txt
archivenow-2020.7.18.12.19.44.dist-info/top_level.txt
archivenow-2020.7.18.12.19.44.dist-info/RECORD
