Metadata-Version: 1.1
Name: archivenow
Version: 2020.7.18.12.19.44
Summary: A Python library to push web resources into public web archives
Home-page: https://github.com/maturban/archivenow
Author: Mohamed Aturban
Author-email: maturban@cs.odu.edu
License: MIT
Platform: UNKNOWN
Classifier: Development Status :: 5 - Production/Stable
Classifier: Programming Language :: Python
Classifier: Programming Language :: Python :: 2.7
Classifier: Programming Language :: Python :: 3
Classifier: Programming Language :: Python :: 3.4
Classifier: Programming Language :: Python :: 3.5
Classifier: Programming Language :: Python :: 3.6
Classifier: License :: OSI Approved :: MIT License
